{
  "id": "87c4347e-6494-46ba-a1eb-50678317b37a",
  "prevId": "4015a72e-e77b-4f00-917a-c54c1a49fcbd",
  "version": "5",
  "dialect": "pg",
  "tables": {
    "account": {
      "name": "account",
      "schema": "",
      "columns": {
        "userId": {
          "name": "userId",
          "type": "uuid",
          "primaryKey": false,
          "notNull": true
        },
        "type": {
          "name": "type",
          "type": "text",
          "primaryKey": false,
          "notNull": true
        },
        "provider": {
          "name": "provider",
          "type": "text",
          "primaryKey": false,
          "notNull": true
        },
        "providerAccountId": {
          "name": "providerAccountId",
          "type": "text",
          "primaryKey": false,
          "notNull": true
        },
        "refresh_token": {
          "name": "refresh_token",
          "type": "text",
          "primaryKey": false,
          "notNull": false
        },
        "access_token": {
          "name": "access_token",
          "type": "text",
          "primaryKey": false,
          "notNull": false
        },
        "expires_at": {
          "name": "expires_at",
          "type": "integer",
          "primaryKey": false,
          "notNull": false
        },
        "token_type": {
          "name": "token_type",
          "type": "text",
          "primaryKey": false,
          "notNull": false
        },
        "scope": {
          "name": "scope",
          "type": "text",
          "primaryKey": false,
          "notNull": false
        },
        "id_token": {
          "name": "id_token",
          "type": "text",
          "primaryKey": false,
          "notNull": false
        },
        "session_state": {
          "name": "session_state",
          "type": "text",
          "primaryKey": false,
          "notNull": false
        }
      },
      "indexes": {},
      "foreignKeys": {
        "account_userId_user_id_fk": {
          "name": "account_userId_user_id_fk",
          "tableFrom": "account",
          "tableTo": "user",
          "columnsFrom": [
            "userId"
          ],
          "columnsTo": [
            "id"
          ],
          "onDelete": "cascade",
          "onUpdate": "no action"
        }
      },
      "compositePrimaryKeys": {
        "account_provider_providerAccountId_pk": {
          "name": "account_provider_providerAccountId_pk",
          "columns": [
            "provider",
            "providerAccountId"
          ]
        }
      },
      "uniqueConstraints": {}
    },
    "anime": {
      "name": "anime",
      "schema": "",
      "columns": {
        "id": {
          "name": "id",
          "type": "uuid",
          "primaryKey": true,
          "notNull": true,
          "default": "gen_random_uuid()"
        },
        "name": {
          "name": "name",
          "type": "text",
          "primaryKey": false,
          "notNull": true
        },
        "other_names": {
          "name": "other_names",
          "type": "text[]",
          "primaryKey": false,
          "notNull": true
        },
        "summary": {
          "name": "summary",
          "type": "jsonb",
          "primaryKey": false,
          "notNull": false
        },
        "created_at": {
          "name": "created_at",
          "type": "timestamp",
          "primaryKey": false,
          "notNull": false,
          "default": "now()"
        },
        "updated_at": {
          "name": "updated_at",
          "type": "timestamp",
          "primaryKey": false,
          "notNull": false,
          "default": "now()"
        },
        "deleted": {
          "name": "deleted",
          "type": "boolean",
          "primaryKey": false,
          "notNull": false,
          "default": false
        },
        "status": {
          "name": "status",
          "type": "text",
          "primaryKey": false,
          "notNull": false
        },
        "note": {
          "name": "note",
          "type": "jsonb",
          "primaryKey": false,
          "notNull": false
        },
        "user_id": {
          "name": "user_id",
          "type": "uuid",
          "primaryKey": false,
          "notNull": true
        },
        "translation_group_id": {
          "name": "translation_group_id",
          "type": "uuid",
          "primaryKey": false,
          "notNull": false
        }
      },
      "indexes": {
        "anime_name_idx": {
          "name": "anime_name_idx",
          "columns": [
            "name"
          ],
          "isUnique": false
        },
        "anime_other_name_idx": {
          "name": "anime_other_name_idx",
          "columns": [
            "other_names"
          ],
          "isUnique": false
        }
      },
      "foreignKeys": {
        "anime_user_id_user_id_fk": {
          "name": "anime_user_id_user_id_fk",
          "tableFrom": "anime",
          "tableTo": "user",
          "columnsFrom": [
            "user_id"
          ],
          "columnsTo": [
            "id"
          ],
          "onDelete": "cascade",
          "onUpdate": "no action"
        },
        "anime_translation_group_id_translation_group_id_fk": {
          "name": "anime_translation_group_id_translation_group_id_fk",
          "tableFrom": "anime",
          "tableTo": "translation_group",
          "columnsFrom": [
            "translation_group_id"
          ],
          "columnsTo": [
            "id"
          ],
          "onDelete": "set null",
          "onUpdate": "no action"
        }
      },
      "compositePrimaryKeys": {},
      "uniqueConstraints": {
        "anime_id_unique": {
          "name": "anime_id_unique",
          "nullsNotDistinct": false,
          "columns": [
            "id"
          ]
        }
      }
    },
    "anime_episode": {
      "name": "anime_episode",
      "schema": "",
      "columns": {
        "id": {
          "name": "id",
          "type": "uuid",
          "primaryKey": true,
          "notNull": true,
          "default": "gen_random_uuid()"
        },
        "content": {
          "name": "content",
          "type": "jsonb",
          "primaryKey": false,
          "notNull": true,
          "default": "'{\"key\":\"\",\"url\":\"\"}'::jsonb"
        },
        "thumbnail": {
          "name": "thumbnail",
          "type": "jsonb",
          "primaryKey": false,
          "notNull": true,
          "default": "'{\"key\":\"\",\"url\":\"\"}'::jsonb"
        },
        "created_at": {
          "name": "created_at",
          "type": "timestamp",
          "primaryKey": false,
          "notNull": false,
          "default": "now()"
        },
        "updated_at": {
          "name": "updated_at",
          "type": "timestamp",
          "primaryKey": false,
          "notNull": false,
          "default": "now()"
        },
        "deleted": {
          "name": "deleted",
          "type": "boolean",
          "primaryKey": false,
          "notNull": false,
          "default": false
        },
        "viewed": {
          "name": "viewed",
          "type": "integer",
          "primaryKey": false,
          "notNull": false,
          "default": 0
        },
        "index": {
          "name": "index",
          "type": "varchar(6)",
          "primaryKey": false,
          "notNull": true
        },
        "viewed_at": {
          "name": "viewed_at",
          "type": "timestamp",
          "primaryKey": false,
          "notNull": false
        },
        "charge": {
          "name": "charge",
          "type": "boolean",
          "primaryKey": false,
          "notNull": false,
          "default": false
        },
        "season_id": {
          "name": "season_id",
          "type": "uuid",
          "primaryKey": false,
          "notNull": true
        }
      },
      "indexes": {},
      "foreignKeys": {
        "anime_episode_season_id_anime_season_id_fk": {
          "name": "anime_episode_season_id_anime_season_id_fk",
          "tableFrom": "anime_episode",
          "tableTo": "anime_season",
          "columnsFrom": [
            "season_id"
          ],
          "columnsTo": [
            "id"
          ],
          "onDelete": "cascade",
          "onUpdate": "no action"
        }
      },
      "compositePrimaryKeys": {},
      "uniqueConstraints": {
        "anime_episode_id_unique": {
          "name": "anime_episode_id_unique",
          "nullsNotDistinct": false,
          "columns": [
            "id"
          ]
        }
      }
    },
    "anime_season": {
      "name": "anime_season",
      "schema": "",
      "columns": {
        "id": {
          "name": "id",
          "type": "uuid",
          "primaryKey": true,
          "notNull": true,
          "default": "gen_random_uuid()"
        },
        "name": {
          "name": "name",
          "type": "text",
          "primaryKey": false,
          "notNull": true
        },
        "created_at": {
          "name": "created_at",
          "type": "timestamp",
          "primaryKey": false,
          "notNull": false,
          "default": "now()"
        },
        "updated_at": {
          "name": "updated_at",
          "type": "timestamp",
          "primaryKey": false,
          "notNull": false,
          "default": "now()"
        },
        "deleted": {
          "name": "deleted",
          "type": "boolean",
          "primaryKey": false,
          "notNull": false,
          "default": false
        },
        "image": {
          "name": "image",
          "type": "jsonb",
          "primaryKey": false,
          "notNull": false,
          "default": "'{\"key\":\"\",\"url\":\"\"}'::jsonb"
        },
        "musics": {
          "name": "musics",
          "type": "jsonb",
          "primaryKey": false,
          "notNull": false,
          "default": "'[]'::jsonb"
        },
        "studio": {
          "name": "studio",
          "type": "text",
          "primaryKey": false,
          "notNull": true
        },
        "broadcast_time": {
          "name": "broadcast_time",
          "type": "timestamp",
          "primaryKey": false,
          "notNull": true
        },
        "broadcast_day": {
          "name": "broadcast_day",
          "type": "varchar(10)",
          "primaryKey": false,
          "notNull": true
        },
        "aired": {
          "name": "aired",
          "type": "date",
          "primaryKey": false,
          "notNull": true
        },
        "number_of_episodes": {
          "name": "number_of_episodes",
          "type": "integer",
          "primaryKey": false,
          "notNull": false
        },
        "anime_id": {
          "name": "anime_id",
          "type": "uuid",
          "primaryKey": false,
          "notNull": true
        }
      },
      "indexes": {},
      "foreignKeys": {
        "anime_season_anime_id_anime_id_fk": {
          "name": "anime_season_anime_id_anime_id_fk",
          "tableFrom": "anime_season",
          "tableTo": "anime",
          "columnsFrom": [
            "anime_id"
          ],
          "columnsTo": [
            "id"
          ],
          "onDelete": "cascade",
          "onUpdate": "no action"
        }
      },
      "compositePrimaryKeys": {},
      "uniqueConstraints": {
        "anime_season_id_unique": {
          "name": "anime_season_id_unique",
          "nullsNotDistinct": false,
          "columns": [
            "id"
          ]
        }
      }
    },
    "category": {
      "name": "category",
      "schema": "",
      "columns": {
        "id": {
          "name": "id",
          "type": "uuid",
          "primaryKey": true,
          "notNull": true,
          "default": "gen_random_uuid()"
        },
        "name": {
          "name": "name",
          "type": "text",
          "primaryKey": false,
          "notNull": true
        }
      },
      "indexes": {},
      "foreignKeys": {},
      "compositePrimaryKeys": {},
      "uniqueConstraints": {
        "category_id_unique": {
          "name": "category_id_unique",
          "nullsNotDistinct": false,
          "columns": [
            "id"
          ]
        }
      }
    },
    "category_anime": {
      "name": "category_anime",
      "schema": "",
      "columns": {
        "category_id": {
          "name": "category_id",
          "type": "uuid",
          "primaryKey": false,
          "notNull": true
        },
        "anime_id": {
          "name": "anime_id",
          "type": "uuid",
          "primaryKey": false,
          "notNull": true
        }
      },
      "indexes": {},
      "foreignKeys": {
        "category_anime_category_id_category_id_fk": {
          "name": "category_anime_category_id_category_id_fk",
          "tableFrom": "category_anime",
          "tableTo": "category",
          "columnsFrom": [
            "category_id"
          ],
          "columnsTo": [
            "id"
          ],
          "onDelete": "no action",
          "onUpdate": "no action"
        },
        "category_anime_anime_id_anime_id_fk": {
          "name": "category_anime_anime_id_anime_id_fk",
          "tableFrom": "category_anime",
          "tableTo": "anime",
          "columnsFrom": [
            "anime_id"
          ],
          "columnsTo": [
            "id"
          ],
          "onDelete": "no action",
          "onUpdate": "no action"
        }
      },
      "compositePrimaryKeys": {
        "category_anime_category_id_anime_id_pk": {
          "name": "category_anime_category_id_anime_id_pk",
          "columns": [
            "category_id",
            "anime_id"
          ]
        }
      },
      "uniqueConstraints": {}
    },
    "category_lightnovel": {
      "name": "category_lightnovel",
      "schema": "",
      "columns": {
        "category_id": {
          "name": "category_id",
          "type": "uuid",
          "primaryKey": false,
          "notNull": true
        },
        "lightnovel_id": {
          "name": "lightnovel_id",
          "type": "uuid",
          "primaryKey": false,
          "notNull": true
        }
      },
      "indexes": {},
      "foreignKeys": {
        "category_lightnovel_category_id_category_id_fk": {
          "name": "category_lightnovel_category_id_category_id_fk",
          "tableFrom": "category_lightnovel",
          "tableTo": "category",
          "columnsFrom": [
            "category_id"
          ],
          "columnsTo": [
            "id"
          ],
          "onDelete": "no action",
          "onUpdate": "no action"
        },
        "category_lightnovel_lightnovel_id_lightnovel_id_fk": {
          "name": "category_lightnovel_lightnovel_id_lightnovel_id_fk",
          "tableFrom": "category_lightnovel",
          "tableTo": "lightnovel",
          "columnsFrom": [
            "lightnovel_id"
          ],
          "columnsTo": [
            "id"
          ],
          "onDelete": "no action",
          "onUpdate": "no action"
        }
      },
      "compositePrimaryKeys": {
        "category_lightnovel_category_id_lightnovel_id_pk": {
          "name": "category_lightnovel_category_id_lightnovel_id_pk",
          "columns": [
            "category_id",
            "lightnovel_id"
          ]
        }
      },
      "uniqueConstraints": {}
    },
    "category_manga": {
      "name": "category_manga",
      "schema": "",
      "columns": {
        "category_id": {
          "name": "category_id",
          "type": "uuid",
          "primaryKey": false,
          "notNull": true
        },
        "manga_id": {
          "name": "manga_id",
          "type": "uuid",
          "primaryKey": false,
          "notNull": true
        }
      },
      "indexes": {},
      "foreignKeys": {
        "category_manga_category_id_category_id_fk": {
          "name": "category_manga_category_id_category_id_fk",
          "tableFrom": "category_manga",
          "tableTo": "category",
          "columnsFrom": [
            "category_id"
          ],
          "columnsTo": [
            "id"
          ],
          "onDelete": "no action",
          "onUpdate": "no action"
        },
        "category_manga_manga_id_manga_id_fk": {
          "name": "category_manga_manga_id_manga_id_fk",
          "tableFrom": "category_manga",
          "tableTo": "manga",
          "columnsFrom": [
            "manga_id"
          ],
          "columnsTo": [
            "id"
          ],
          "onDelete": "no action",
          "onUpdate": "no action"
        }
      },
      "compositePrimaryKeys": {
        "category_manga_category_id_manga_id_pk": {
          "name": "category_manga_category_id_manga_id_pk",
          "columns": [
            "category_id",
            "manga_id"
          ]
        }
      },
      "uniqueConstraints": {}
    },
    "comment": {
      "name": "comment",
      "schema": "",
      "columns": {
        "id": {
          "name": "id",
          "type": "uuid",
          "primaryKey": true,
          "notNull": true,
          "default": "gen_random_uuid()"
        },
        "parent_id": {
          "name": "parent_id",
          "type": "uuid",
          "primaryKey": false,
          "notNull": false
        },
        "comment": {
          "name": "comment",
          "type": "text",
          "primaryKey": false,
          "notNull": true
        },
        "user_id": {
          "name": "user_id",
          "type": "uuid",
          "primaryKey": false,
          "notNull": true
        },
        "created_at": {
          "name": "created_at",
          "type": "timestamp",
          "primaryKey": false,
          "notNull": false,
          "default": "now()"
        },
        "updated_at": {
          "name": "updated_at",
          "type": "timestamp",
          "primaryKey": false,
          "notNull": false,
          "default": "now()"
        },
        "deleted": {
          "name": "deleted",
          "type": "boolean",
          "primaryKey": false,
          "notNull": false,
          "default": false
        }
      },
      "indexes": {},
      "foreignKeys": {
        "comment_user_id_user_id_fk": {
          "name": "comment_user_id_user_id_fk",
          "tableFrom": "comment",
          "tableTo": "user",
          "columnsFrom": [
            "user_id"
          ],
          "columnsTo": [
            "id"
          ],
          "onDelete": "cascade",
          "onUpdate": "no action"
        }
      },
      "compositePrimaryKeys": {},
      "uniqueConstraints": {
        "comment_id_unique": {
          "name": "comment_id_unique",
          "nullsNotDistinct": false,
          "columns": [
            "id"
          ]
        }
      }
    },
    "comment_anime": {
      "name": "comment_anime",
      "schema": "",
      "columns": {
        "comment_id": {
          "name": "comment_id",
          "type": "uuid",
          "primaryKey": false,
          "notNull": true
        },
        "anime_id": {
          "name": "anime_id",
          "type": "uuid",
          "primaryKey": false,
          "notNull": true
        }
      },
      "indexes": {},
      "foreignKeys": {
        "comment_anime_comment_id_comment_id_fk": {
          "name": "comment_anime_comment_id_comment_id_fk",
          "tableFrom": "comment_anime",
          "tableTo": "comment",
          "columnsFrom": [
            "comment_id"
          ],
          "columnsTo": [
            "id"
          ],
          "onDelete": "no action",
          "onUpdate": "no action"
        },
        "comment_anime_anime_id_anime_id_fk": {
          "name": "comment_anime_anime_id_anime_id_fk",
          "tableFrom": "comment_anime",
          "tableTo": "anime",
          "columnsFrom": [
            "anime_id"
          ],
          "columnsTo": [
            "id"
          ],
          "onDelete": "no action",
          "onUpdate": "no action"
        }
      },
      "compositePrimaryKeys": {
        "comment_anime_comment_id_anime_id_pk": {
          "name": "comment_anime_comment_id_anime_id_pk",
          "columns": [
            "comment_id",
            "anime_id"
          ]
        }
      },
      "uniqueConstraints": {}
    },
    "comment_anime_episode": {
      "name": "comment_anime_episode",
      "schema": "",
      "columns": {
        "comment_id": {
          "name": "comment_id",
          "type": "uuid",
          "primaryKey": false,
          "notNull": true
        },
        "episode_id": {
          "name": "episode_id",
          "type": "uuid",
          "primaryKey": false,
          "notNull": true
        }
      },
      "indexes": {},
      "foreignKeys": {
        "comment_anime_episode_comment_id_comment_id_fk": {
          "name": "comment_anime_episode_comment_id_comment_id_fk",
          "tableFrom": "comment_anime_episode",
          "tableTo": "comment",
          "columnsFrom": [
            "comment_id"
          ],
          "columnsTo": [
            "id"
          ],
          "onDelete": "no action",
          "onUpdate": "no action"
        },
        "comment_anime_episode_episode_id_anime_episode_id_fk": {
          "name": "comment_anime_episode_episode_id_anime_episode_id_fk",
          "tableFrom": "comment_anime_episode",
          "tableTo": "anime_episode",
          "columnsFrom": [
            "episode_id"
          ],
          "columnsTo": [
            "id"
          ],
          "onDelete": "no action",
          "onUpdate": "no action"
        }
      },
      "compositePrimaryKeys": {
        "comment_anime_episode_comment_id_episode_id_pk": {
          "name": "comment_anime_episode_comment_id_episode_id_pk",
          "columns": [
            "comment_id",
            "episode_id"
          ]
        }
      },
      "uniqueConstraints": {}
    },
    "comment_lightnovel": {
      "name": "comment_lightnovel",
      "schema": "",
      "columns": {
        "comment_id": {
          "name": "comment_id",
          "type": "uuid",
          "primaryKey": false,
          "notNull": true
        },
        "lightnovel_id": {
          "name": "lightnovel_id",
          "type": "uuid",
          "primaryKey": false,
          "notNull": true
        }
      },
      "indexes": {},
      "foreignKeys": {
        "comment_lightnovel_comment_id_comment_id_fk": {
          "name": "comment_lightnovel_comment_id_comment_id_fk",
          "tableFrom": "comment_lightnovel",
          "tableTo": "comment",
          "columnsFrom": [
            "comment_id"
          ],
          "columnsTo": [
            "id"
          ],
          "onDelete": "no action",
          "onUpdate": "no action"
        },
        "comment_lightnovel_lightnovel_id_lightnovel_id_fk": {
          "name": "comment_lightnovel_lightnovel_id_lightnovel_id_fk",
          "tableFrom": "comment_lightnovel",
          "tableTo": "lightnovel",
          "columnsFrom": [
            "lightnovel_id"
          ],
          "columnsTo": [
            "id"
          ],
          "onDelete": "no action",
          "onUpdate": "no action"
        }
      },
      "compositePrimaryKeys": {
        "comment_lightnovel_comment_id_lightnovel_id_pk": {
          "name": "comment_lightnovel_comment_id_lightnovel_id_pk",
          "columns": [
            "comment_id",
            "lightnovel_id"
          ]
        }
      },
      "uniqueConstraints": {}
    },
    "comment_lightnovel_chapter": {
      "name": "comment_lightnovel_chapter",
      "schema": "",
      "columns": {
        "comment_id": {
          "name": "comment_id",
          "type": "uuid",
          "primaryKey": false,
          "notNull": true
        },
        "chapter_id": {
          "name": "chapter_id",
          "type": "uuid",
          "primaryKey": false,
          "notNull": true
        }
      },
      "indexes": {},
      "foreignKeys": {
        "comment_lightnovel_chapter_comment_id_comment_id_fk": {
          "name": "comment_lightnovel_chapter_comment_id_comment_id_fk",
          "tableFrom": "comment_lightnovel_chapter",
          "tableTo": "comment",
          "columnsFrom": [
            "comment_id"
          ],
          "columnsTo": [
            "id"
          ],
          "onDelete": "no action",
          "onUpdate": "no action"
        },
        "comment_lightnovel_chapter_chapter_id_lightnovel_chapter_id_fk": {
          "name": "comment_lightnovel_chapter_chapter_id_lightnovel_chapter_id_fk",
          "tableFrom": "comment_lightnovel_chapter",
          "tableTo": "lightnovel_chapter",
          "columnsFrom": [
            "chapter_id"
          ],
          "columnsTo": [
            "id"
          ],
          "onDelete": "no action",
          "onUpdate": "no action"
        }
      },
      "compositePrimaryKeys": {
        "comment_lightnovel_chapter_comment_id_chapter_id_pk": {
          "name": "comment_lightnovel_chapter_comment_id_chapter_id_pk",
          "columns": [
            "comment_id",
            "chapter_id"
          ]
        }
      },
      "uniqueConstraints": {}
    },
    "comment_manga": {
      "name": "comment_manga",
      "schema": "",
      "columns": {
        "comment_id": {
          "name": "comment_id",
          "type": "uuid",
          "primaryKey": false,
          "notNull": true
        },
        "manga_id": {
          "name": "manga_id",
          "type": "uuid",
          "primaryKey": false,
          "notNull": true
        }
      },
      "indexes": {},
      "foreignKeys": {
        "comment_manga_comment_id_comment_id_fk": {
          "name": "comment_manga_comment_id_comment_id_fk",
          "tableFrom": "comment_manga",
          "tableTo": "comment",
          "columnsFrom": [
            "comment_id"
          ],
          "columnsTo": [
            "id"
          ],
          "onDelete": "no action",
          "onUpdate": "no action"
        },
        "comment_manga_manga_id_manga_id_fk": {
          "name": "comment_manga_manga_id_manga_id_fk",
          "tableFrom": "comment_manga",
          "tableTo": "manga",
          "columnsFrom": [
            "manga_id"
          ],
          "columnsTo": [
            "id"
          ],
          "onDelete": "no action",
          "onUpdate": "no action"
        }
      },
      "compositePrimaryKeys": {
        "comment_manga_comment_id_manga_id_pk": {
          "name": "comment_manga_comment_id_manga_id_pk",
          "columns": [
            "comment_id",
            "manga_id"
          ]
        }
      },
      "uniqueConstraints": {}
    },
    "comment_manga_chapter": {
      "name": "comment_manga_chapter",
      "schema": "",
      "columns": {
        "comment_id": {
          "name": "comment_id",
          "type": "uuid",
          "primaryKey": false,
          "notNull": true
        },
        "chapter_id": {
          "name": "chapter_id",
          "type": "uuid",
          "primaryKey": false,
          "notNull": true
        }
      },
      "indexes": {},
      "foreignKeys": {
        "comment_manga_chapter_comment_id_comment_id_fk": {
          "name": "comment_manga_chapter_comment_id_comment_id_fk",
          "tableFrom": "comment_manga_chapter",
          "tableTo": "comment",
          "columnsFrom": [
            "comment_id"
          ],
          "columnsTo": [
            "id"
          ],
          "onDelete": "no action",
          "onUpdate": "no action"
        },
        "comment_manga_chapter_chapter_id_manga_chapter_id_fk": {
          "name": "comment_manga_chapter_chapter_id_manga_chapter_id_fk",
          "tableFrom": "comment_manga_chapter",
          "tableTo": "manga_chapter",
          "columnsFrom": [
            "chapter_id"
          ],
          "columnsTo": [
            "id"
          ],
          "onDelete": "no action",
          "onUpdate": "no action"
        }
      },
      "compositePrimaryKeys": {
        "comment_manga_chapter_comment_id_chapter_id_pk": {
          "name": "comment_manga_chapter_comment_id_chapter_id_pk",
          "columns": [
            "comment_id",
            "chapter_id"
          ]
        }
      },
      "uniqueConstraints": {}
    },
    "favorite_comment": {
      "name": "favorite_comment",
      "schema": "",
      "columns": {
        "comment_id": {
          "name": "comment_id",
          "type": "uuid",
          "primaryKey": false,
          "notNull": true
        },
        "user_id": {
          "name": "user_id",
          "type": "uuid",
          "primaryKey": false,
          "notNull": true
        }
      },
      "indexes": {},
      "foreignKeys": {
        "favorite_comment_comment_id_comment_id_fk": {
          "name": "favorite_comment_comment_id_comment_id_fk",
          "tableFrom": "favorite_comment",
          "tableTo": "comment",
          "columnsFrom": [
            "comment_id"
          ],
          "columnsTo": [
            "id"
          ],
          "onDelete": "no action",
          "onUpdate": "no action"
        },
        "favorite_comment_user_id_user_id_fk": {
          "name": "favorite_comment_user_id_user_id_fk",
          "tableFrom": "favorite_comment",
          "tableTo": "user",
          "columnsFrom": [
            "user_id"
          ],
          "columnsTo": [
            "id"
          ],
          "onDelete": "no action",
          "onUpdate": "no action"
        }
      },
      "compositePrimaryKeys": {},
      "uniqueConstraints": {}
    },
    "favorite_anime": {
      "name": "favorite_anime",
      "schema": "",
      "columns": {
        "user_id": {
          "name": "user_id",
          "type": "uuid",
          "primaryKey": false,
          "notNull": true
        },
        "anime_id": {
          "name": "anime_id",
          "type": "uuid",
          "primaryKey": false,
          "notNull": true
        }
      },
      "indexes": {
        "user_anime_fav_idx": {
          "name": "user_anime_fav_idx",
          "columns": [
            "user_id"
          ],
          "isUnique": false
        }
      },
      "foreignKeys": {
        "favorite_anime_user_id_user_id_fk": {
          "name": "favorite_anime_user_id_user_id_fk",
          "tableFrom": "favorite_anime",
          "tableTo": "user",
          "columnsFrom": [
            "user_id"
          ],
          "columnsTo": [
            "id"
          ],
          "onDelete": "no action",
          "onUpdate": "no action"
        },
        "favorite_anime_anime_id_anime_id_fk": {
          "name": "favorite_anime_anime_id_anime_id_fk",
          "tableFrom": "favorite_anime",
          "tableTo": "anime",
          "columnsFrom": [
            "anime_id"
          ],
          "columnsTo": [
            "id"
          ],
          "onDelete": "no action",
          "onUpdate": "no action"
        }
      },
      "compositePrimaryKeys": {
        "favorite_anime_user_id_anime_id_pk": {
          "name": "favorite_anime_user_id_anime_id_pk",
          "columns": [
            "user_id",
            "anime_id"
          ]
        }
      },
      "uniqueConstraints": {}
    },
    "favorite_lightnovel": {
      "name": "favorite_lightnovel",
      "schema": "",
      "columns": {
        "user_id": {
          "name": "user_id",
          "type": "uuid",
          "primaryKey": false,
          "notNull": true
        },
        "lightnovel_id": {
          "name": "lightnovel_id",
          "type": "uuid",
          "primaryKey": false,
          "notNull": true
        }
      },
      "indexes": {
        "user_lightnovel_fav_idx": {
          "name": "user_lightnovel_fav_idx",
          "columns": [
            "user_id"
          ],
          "isUnique": false
        }
      },
      "foreignKeys": {
        "favorite_lightnovel_user_id_user_id_fk": {
          "name": "favorite_lightnovel_user_id_user_id_fk",
          "tableFrom": "favorite_lightnovel",
          "tableTo": "user",
          "columnsFrom": [
            "user_id"
          ],
          "columnsTo": [
            "id"
          ],
          "onDelete": "no action",
          "onUpdate": "no action"
        },
        "favorite_lightnovel_lightnovel_id_lightnovel_id_fk": {
          "name": "favorite_lightnovel_lightnovel_id_lightnovel_id_fk",
          "tableFrom": "favorite_lightnovel",
          "tableTo": "lightnovel",
          "columnsFrom": [
            "lightnovel_id"
          ],
          "columnsTo": [
            "id"
          ],
          "onDelete": "no action",
          "onUpdate": "no action"
        }
      },
      "compositePrimaryKeys": {
        "favorite_lightnovel_user_id_lightnovel_id_pk": {
          "name": "favorite_lightnovel_user_id_lightnovel_id_pk",
          "columns": [
            "user_id",
            "lightnovel_id"
          ]
        }
      },
      "uniqueConstraints": {}
    },
    "favorite_manga": {
      "name": "favorite_manga",
      "schema": "",
      "columns": {
        "user_id": {
          "name": "user_id",
          "type": "uuid",
          "primaryKey": false,
          "notNull": true
        },
        "manga_id": {
          "name": "manga_id",
          "type": "uuid",
          "primaryKey": false,
          "notNull": true
        }
      },
      "indexes": {
        "user_manga_fav_idx": {
          "name": "user_manga_fav_idx",
          "columns": [
            "user_id"
          ],
          "isUnique": false
        }
      },
      "foreignKeys": {
        "favorite_manga_user_id_user_id_fk": {
          "name": "favorite_manga_user_id_user_id_fk",
          "tableFrom": "favorite_manga",
          "tableTo": "user",
          "columnsFrom": [
            "user_id"
          ],
          "columnsTo": [
            "id"
          ],
          "onDelete": "no action",
          "onUpdate": "no action"
        },
        "favorite_manga_manga_id_manga_id_fk": {
          "name": "favorite_manga_manga_id_manga_id_fk",
          "tableFrom": "favorite_manga",
          "tableTo": "manga",
          "columnsFrom": [
            "manga_id"
          ],
          "columnsTo": [
            "id"
          ],
          "onDelete": "no action",
          "onUpdate": "no action"
        }
      },
      "compositePrimaryKeys": {
        "favorite_manga_user_id_manga_id_pk": {
          "name": "favorite_manga_user_id_manga_id_pk",
          "columns": [
            "user_id",
            "manga_id"
          ]
        }
      },
      "uniqueConstraints": {}
    },
    "follower_group": {
      "name": "follower_group",
      "schema": "",
      "columns": {
        "follower_id": {
          "name": "follower_id",
          "type": "uuid",
          "primaryKey": false,
          "notNull": true
        },
        "followed_id": {
          "name": "followed_id",
          "type": "uuid",
          "primaryKey": false,
          "notNull": true
        }
      },
      "indexes": {},
      "foreignKeys": {
        "follower_group_follower_id_user_id_fk": {
          "name": "follower_group_follower_id_user_id_fk",
          "tableFrom": "follower_group",
          "tableTo": "user",
          "columnsFrom": [
            "follower_id"
          ],
          "columnsTo": [
            "id"
          ],
          "onDelete": "no action",
          "onUpdate": "no action"
        },
        "follower_group_followed_id_translation_group_id_fk": {
          "name": "follower_group_followed_id_translation_group_id_fk",
          "tableFrom": "follower_group",
          "tableTo": "translation_group",
          "columnsFrom": [
            "followed_id"
          ],
          "columnsTo": [
            "id"
          ],
          "onDelete": "no action",
          "onUpdate": "no action"
        }
      },
      "compositePrimaryKeys": {
        "follower_group_follower_id_followed_id_pk": {
          "name": "follower_group_follower_id_followed_id_pk",
          "columns": [
            "follower_id",
            "followed_id"
          ]
        }
      },
      "uniqueConstraints": {}
    },
    "follower_user": {
      "name": "follower_user",
      "schema": "",
      "columns": {
        "followed_by": {
          "name": "followed_by",
          "type": "uuid",
          "primaryKey": false,
          "notNull": true
        },
        "following": {
          "name": "following",
          "type": "uuid",
          "primaryKey": false,
          "notNull": true
        }
      },
      "indexes": {},
      "foreignKeys": {
        "follower_user_followed_by_user_id_fk": {
          "name": "follower_user_followed_by_user_id_fk",
          "tableFrom": "follower_user",
          "tableTo": "user",
          "columnsFrom": [
            "followed_by"
          ],
          "columnsTo": [
            "id"
          ],
          "onDelete": "cascade",
          "onUpdate": "no action"
        },
        "follower_user_following_user_id_fk": {
          "name": "follower_user_following_user_id_fk",
          "tableFrom": "follower_user",
          "tableTo": "user",
          "columnsFrom": [
            "following"
          ],
          "columnsTo": [
            "id"
          ],
          "onDelete": "cascade",
          "onUpdate": "no action"
        }
      },
      "compositePrimaryKeys": {
        "follower_user_followed_by_following_pk": {
          "name": "follower_user_followed_by_following_pk",
          "columns": [
            "followed_by",
            "following"
          ]
        }
      },
      "uniqueConstraints": {}
    },
    "lightnovel": {
      "name": "lightnovel",
      "schema": "",
      "columns": {
        "id": {
          "name": "id",
          "type": "uuid",
          "primaryKey": true,
          "notNull": true,
          "default": "gen_random_uuid()"
        },
        "name": {
          "name": "name",
          "type": "text",
          "primaryKey": false,
          "notNull": true
        },
        "other_names": {
          "name": "other_names",
          "type": "text[]",
          "primaryKey": false,
          "notNull": true
        },
        "author": {
          "name": "author",
          "type": "varchar(70)",
          "primaryKey": false,
          "notNull": false
        },
        "artist": {
          "name": "artist",
          "type": "varchar(70)",
          "primaryKey": false,
          "notNull": false
        },
        "image": {
          "name": "image",
          "type": "jsonb",
          "primaryKey": false,
          "notNull": false,
          "default": "'{\"key\":\"\",\"url\":\"\"}'::jsonb"
        },
        "summary": {
          "name": "summary",
          "type": "jsonb",
          "primaryKey": false,
          "notNull": false
        },
        "created_at": {
          "name": "created_at",
          "type": "timestamp",
          "primaryKey": false,
          "notNull": false,
          "default": "now()"
        },
        "updated_at": {
          "name": "updated_at",
          "type": "timestamp",
          "primaryKey": false,
          "notNull": false,
          "default": "now()"
        },
        "deleted": {
          "name": "deleted",
          "type": "boolean",
          "primaryKey": false,
          "notNull": false,
          "default": false
        },
        "status": {
          "name": "status",
          "type": "text",
          "primaryKey": false,
          "notNull": false
        },
        "note": {
          "name": "note",
          "type": "jsonb",
          "primaryKey": false,
          "notNull": false
        },
        "user_id": {
          "name": "user_id",
          "type": "uuid",
          "primaryKey": false,
          "notNull": true
        },
        "translation_group_id": {
          "name": "translation_group_id",
          "type": "uuid",
          "primaryKey": false,
          "notNull": false
        }
      },
      "indexes": {
        "lightnovel_name_idx": {
          "name": "lightnovel_name_idx",
          "columns": [
            "name"
          ],
          "isUnique": false
        },
        "lightnovel_other_name_idx": {
          "name": "lightnovel_other_name_idx",
          "columns": [
            "other_names"
          ],
          "isUnique": false
        }
      },
      "foreignKeys": {
        "lightnovel_user_id_user_id_fk": {
          "name": "lightnovel_user_id_user_id_fk",
          "tableFrom": "lightnovel",
          "tableTo": "user",
          "columnsFrom": [
            "user_id"
          ],
          "columnsTo": [
            "id"
          ],
          "onDelete": "cascade",
          "onUpdate": "no action"
        },
        "lightnovel_translation_group_id_translation_group_id_fk": {
          "name": "lightnovel_translation_group_id_translation_group_id_fk",
          "tableFrom": "lightnovel",
          "tableTo": "translation_group",
          "columnsFrom": [
            "translation_group_id"
          ],
          "columnsTo": [
            "id"
          ],
          "onDelete": "set null",
          "onUpdate": "no action"
        }
      },
      "compositePrimaryKeys": {},
      "uniqueConstraints": {
        "lightnovel_id_unique": {
          "name": "lightnovel_id_unique",
          "nullsNotDistinct": false,
          "columns": [
            "id"
          ]
        }
      }
    },
    "lightnovel_chapter": {
      "name": "lightnovel_chapter",
      "schema": "",
      "columns": {
        "id": {
          "name": "id",
          "type": "uuid",
          "primaryKey": true,
          "notNull": true,
          "default": "gen_random_uuid()"
        },
        "name": {
          "name": "name",
          "type": "text",
          "primaryKey": false,
          "notNull": true
        },
        "content": {
          "name": "content",
          "type": "jsonb",
          "primaryKey": false,
          "notNull": true
        },
        "created_at": {
          "name": "created_at",
          "type": "timestamp",
          "primaryKey": false,
          "notNull": false,
          "default": "now()"
        },
        "updated_at": {
          "name": "updated_at",
          "type": "timestamp",
          "primaryKey": false,
          "notNull": false,
          "default": "now()"
        },
        "deleted": {
          "name": "deleted",
          "type": "boolean",
          "primaryKey": false,
          "notNull": false,
          "default": false
        },
        "viewed": {
          "name": "viewed",
          "type": "integer",
          "primaryKey": false,
          "notNull": false,
          "default": 0
        },
        "words": {
          "name": "words",
          "type": "integer",
          "primaryKey": false,
          "notNull": false,
          "default": 0
        },
        "viewed_at": {
          "name": "viewed_at",
          "type": "timestamp",
          "primaryKey": false,
          "notNull": false
        },
        "charge": {
          "name": "charge",
          "type": "boolean",
          "primaryKey": false,
          "notNull": false,
          "default": false
        },
        "volume_id": {
          "name": "volume_id",
          "type": "uuid",
          "primaryKey": false,
          "notNull": true
        }
      },
      "indexes": {},
      "foreignKeys": {
        "lightnovel_chapter_volume_id_lightnovel_volume_id_fk": {
          "name": "lightnovel_chapter_volume_id_lightnovel_volume_id_fk",
          "tableFrom": "lightnovel_chapter",
          "tableTo": "lightnovel_volume",
          "columnsFrom": [
            "volume_id"
          ],
          "columnsTo": [
            "id"
          ],
          "onDelete": "cascade",
          "onUpdate": "no action"
        }
      },
      "compositePrimaryKeys": {},
      "uniqueConstraints": {
        "lightnovel_chapter_id_unique": {
          "name": "lightnovel_chapter_id_unique",
          "nullsNotDistinct": false,
          "columns": [
            "id"
          ]
        }
      }
    },
    "lightnovel_volume": {
      "name": "lightnovel_volume",
      "schema": "",
      "columns": {
        "id": {
          "name": "id",
          "type": "uuid",
          "primaryKey": true,
          "notNull": true,
          "default": "gen_random_uuid()"
        },
        "name": {
          "name": "name",
          "type": "text",
          "primaryKey": false,
          "notNull": true
        },
        "created_at": {
          "name": "created_at",
          "type": "timestamp",
          "primaryKey": false,
          "notNull": false,
          "default": "now()"
        },
        "updated_at": {
          "name": "updated_at",
          "type": "timestamp",
          "primaryKey": false,
          "notNull": false,
          "default": "now()"
        },
        "image": {
          "name": "image",
          "type": "jsonb",
          "primaryKey": false,
          "notNull": false,
          "default": "'{\"key\":\"\",\"url\":\"\"}'::jsonb"
        },
        "deleted": {
          "name": "deleted",
          "type": "boolean",
          "primaryKey": false,
          "notNull": false,
          "default": false
        },
        "lightnovel_id": {
          "name": "lightnovel_id",
          "type": "uuid",
          "primaryKey": false,
          "notNull": true
        }
      },
      "indexes": {},
      "foreignKeys": {
        "lightnovel_volume_lightnovel_id_lightnovel_id_fk": {
          "name": "lightnovel_volume_lightnovel_id_lightnovel_id_fk",
          "tableFrom": "lightnovel_volume",
          "tableTo": "lightnovel",
          "columnsFrom": [
            "lightnovel_id"
          ],
          "columnsTo": [
            "id"
          ],
          "onDelete": "cascade",
          "onUpdate": "no action"
        }
      },
      "compositePrimaryKeys": {},
      "uniqueConstraints": {
        "lightnovel_volume_id_unique": {
          "name": "lightnovel_volume_id_unique",
          "nullsNotDistinct": false,
          "columns": [
            "id"
          ]
        }
      }
    },
    "manga": {
      "name": "manga",
      "schema": "",
      "columns": {
        "id": {
          "name": "id",
          "type": "uuid",
          "primaryKey": true,
          "notNull": true,
          "default": "gen_random_uuid()"
        },
        "name": {
          "name": "name",
          "type": "text",
          "primaryKey": false,
          "notNull": true
        },
        "other_names": {
          "name": "other_names",
          "type": "text[]",
          "primaryKey": false,
          "notNull": true
        },
        "summary": {
          "name": "summary",
          "type": "jsonb",
          "primaryKey": false,
          "notNull": false
        },
        "created_at": {
          "name": "created_at",
          "type": "timestamp",
          "primaryKey": false,
          "notNull": false,
          "default": "now()"
        },
        "updated_at": {
          "name": "updated_at",
          "type": "timestamp",
          "primaryKey": false,
          "notNull": false,
          "default": "now()"
        },
        "deleted": {
          "name": "deleted",
          "type": "boolean",
          "primaryKey": false,
          "notNull": false,
          "default": false
        },
        "status": {
          "name": "status",
          "type": "text",
          "primaryKey": false,
          "notNull": false
        },
        "note": {
          "name": "note",
          "type": "jsonb",
          "primaryKey": false,
          "notNull": false
        },
        "user_id": {
          "name": "user_id",
          "type": "uuid",
          "primaryKey": false,
          "notNull": true
        },
        "translation_group_id": {
          "name": "translation_group_id",
          "type": "uuid",
          "primaryKey": false,
          "notNull": false
        }
      },
      "indexes": {
        "manga_name_idx": {
          "name": "manga_name_idx",
          "columns": [
            "name"
          ],
          "isUnique": false
        },
        "manga_other_name_idx": {
          "name": "manga_other_name_idx",
          "columns": [
            "other_names"
          ],
          "isUnique": false
        }
      },
      "foreignKeys": {
        "manga_user_id_user_id_fk": {
          "name": "manga_user_id_user_id_fk",
          "tableFrom": "manga",
          "tableTo": "user",
          "columnsFrom": [
            "user_id"
          ],
          "columnsTo": [
            "id"
          ],
          "onDelete": "cascade",
          "onUpdate": "no action"
        },
        "manga_translation_group_id_translation_group_id_fk": {
          "name": "manga_translation_group_id_translation_group_id_fk",
          "tableFrom": "manga",
          "tableTo": "translation_group",
          "columnsFrom": [
            "translation_group_id"
          ],
          "columnsTo": [
            "id"
          ],
          "onDelete": "set null",
          "onUpdate": "no action"
        }
      },
      "compositePrimaryKeys": {},
      "uniqueConstraints": {
        "manga_id_unique": {
          "name": "manga_id_unique",
          "nullsNotDistinct": false,
          "columns": [
            "id"
          ]
        }
      }
    },
    "manga_chapter": {
      "name": "manga_chapter",
      "schema": "",
      "columns": {
        "id": {
          "name": "id",
          "type": "uuid",
          "primaryKey": true,
          "notNull": true,
          "default": "gen_random_uuid()"
        },
        "name": {
          "name": "name",
          "type": "text",
          "primaryKey": false,
          "notNull": true
        },
        "content": {
          "name": "content",
          "type": "jsonb",
          "primaryKey": false,
          "notNull": true,
          "default": "'{\"key\":\"\",\"url\":\"\"}'::jsonb"
        },
        "thumbnail": {
          "name": "thumbnail",
          "type": "jsonb",
          "primaryKey": false,
          "notNull": true,
          "default": "'{\"key\":\"\",\"url\":\"\"}'::jsonb"
        },
        "created_at": {
          "name": "created_at",
          "type": "timestamp",
          "primaryKey": false,
          "notNull": false
        },
        "updated_at": {
          "name": "updated_at",
          "type": "timestamp",
          "primaryKey": false,
          "notNull": false,
          "default": "now()"
        },
        "deleted": {
          "name": "deleted",
          "type": "boolean",
          "primaryKey": false,
          "notNull": false,
          "default": false
        },
        "viewed": {
          "name": "viewed",
          "type": "integer",
          "primaryKey": false,
          "notNull": false,
          "default": 0
        },
        "index": {
          "name": "index",
          "type": "varchar(6)",
          "primaryKey": false,
          "notNull": false
        },
        "charge": {
          "name": "charge",
          "type": "boolean",
          "primaryKey": false,
          "notNull": false,
          "default": false
        },
        "season_id": {
          "name": "season_id",
          "type": "uuid",
          "primaryKey": false,
          "notNull": true
        }
      },
      "indexes": {},
      "foreignKeys": {
        "manga_chapter_season_id_manga_season_id_fk": {
          "name": "manga_chapter_season_id_manga_season_id_fk",
          "tableFrom": "manga_chapter",
          "tableTo": "manga_season",
          "columnsFrom": [
            "season_id"
          ],
          "columnsTo": [
            "id"
          ],
          "onDelete": "cascade",
          "onUpdate": "no action"
        }
      },
      "compositePrimaryKeys": {},
      "uniqueConstraints": {
        "manga_chapter_id_unique": {
          "name": "manga_chapter_id_unique",
          "nullsNotDistinct": false,
          "columns": [
            "id"
          ]
        }
      }
    },
    "manga_season": {
      "name": "manga_season",
      "schema": "",
      "columns": {
        "id": {
          "name": "id",
          "type": "uuid",
          "primaryKey": true,
          "notNull": true,
          "default": "gen_random_uuid()"
        },
        "name": {
          "name": "name",
          "type": "text",
          "primaryKey": false,
          "notNull": true
        },
        "created_at": {
          "name": "created_at",
          "type": "timestamp",
          "primaryKey": false,
          "notNull": false,
          "default": "now()"
        },
        "updated_at": {
          "name": "updated_at",
          "type": "timestamp",
          "primaryKey": false,
          "notNull": false,
          "default": "now()"
        },
        "deleted": {
          "name": "deleted",
          "type": "boolean",
          "primaryKey": false,
          "notNull": false,
          "default": false
        },
        "image": {
          "name": "image",
          "type": "jsonb",
          "primaryKey": false,
          "notNull": false,
          "default": "'{\"key\":\"\",\"url\":\"\"}'::jsonb"
        },
        "musics": {
          "name": "musics",
          "type": "jsonb",
          "primaryKey": false,
          "notNull": false,
          "default": "'[]'::jsonb"
        },
        "studio": {
          "name": "studio",
          "type": "text",
          "primaryKey": false,
          "notNull": true
        },
        "broadcast_time": {
          "name": "broadcast_time",
          "type": "date",
          "primaryKey": false,
          "notNull": true
        },
        "broadcast_day": {
          "name": "broadcast_day",
          "type": "varchar(10)",
          "primaryKey": false,
          "notNull": true
        },
        "aired": {
          "name": "aired",
          "type": "date",
          "primaryKey": false,
          "notNull": true
        },
        "number_of_episodes": {
          "name": "number_of_episodes",
          "type": "integer",
          "primaryKey": false,
          "notNull": false
        },
        "manga_id": {
          "name": "manga_id",
          "type": "uuid",
          "primaryKey": false,
          "notNull": true
        }
      },
      "indexes": {},
      "foreignKeys": {
        "manga_season_manga_id_manga_id_fk": {
          "name": "manga_season_manga_id_manga_id_fk",
          "tableFrom": "manga_season",
          "tableTo": "manga",
          "columnsFrom": [
            "manga_id"
          ],
          "columnsTo": [
            "id"
          ],
          "onDelete": "cascade",
          "onUpdate": "no action"
        }
      },
      "compositePrimaryKeys": {},
      "uniqueConstraints": {
        "manga_season_id_unique": {
          "name": "manga_season_id_unique",
          "nullsNotDistinct": false,
          "columns": [
            "id"
          ]
        }
      }
    },
    "payments": {
      "name": "payments",
      "schema": "",
      "columns": {
        "id": {
          "name": "id",
          "type": "uuid",
          "primaryKey": true,
          "notNull": true,
          "default": "gen_random_uuid()"
        },
        "user_id": {
          "name": "user_id",
          "type": "uuid",
          "primaryKey": false,
          "notNull": true
        },
        "code": {
          "name": "code",
          "type": "text",
          "primaryKey": false,
          "notNull": true
        },
        "service": {
          "name": "service",
          "type": "text",
          "primaryKey": false,
          "notNull": true
        },
        "amount": {
          "name": "amount",
          "type": "integer",
          "primaryKey": false,
          "notNull": false
        },
        "pay_date": {
          "name": "pay_date",
          "type": "timestamp",
          "primaryKey": false,
          "notNull": false
        },
        "bank_code": {
          "name": "bank_code",
          "type": "text",
          "primaryKey": false,
          "notNull": false
        },
        "bank_transaction_code": {
          "name": "bank_transaction_code",
          "type": "text",
          "primaryKey": false,
          "notNull": false
        },
        "card_type": {
          "name": "card_type",
          "type": "text",
          "primaryKey": false,
          "notNull": false
        },
        "status": {
          "name": "status",
          "type": "text",
          "primaryKey": false,
          "notNull": false,
          "default": "'pending'"
        },
        "created_at": {
          "name": "created_at",
          "type": "timestamp",
          "primaryKey": false,
          "notNull": false,
          "default": "now()"
        }
      },
      "indexes": {},
      "foreignKeys": {
        "payments_user_id_user_id_fk": {
          "name": "payments_user_id_user_id_fk",
          "tableFrom": "payments",
          "tableTo": "user",
          "columnsFrom": [
            "user_id"
          ],
          "columnsTo": [
            "id"
          ],
          "onDelete": "cascade",
          "onUpdate": "no action"
        }
      },
      "compositePrimaryKeys": {},
      "uniqueConstraints": {
        "payments_id_unique": {
          "name": "payments_id_unique",
          "nullsNotDistinct": false,
          "columns": [
            "id"
          ]
        }
      }
    },
    "permission": {
      "name": "permission",
      "schema": "",
      "columns": {
        "id": {
          "name": "id",
          "type": "uuid",
          "primaryKey": true,
          "notNull": true,
          "default": "gen_random_uuid()"
        },
        "name": {
          "name": "name",
          "type": "text",
          "primaryKey": false,
          "notNull": true
        }
      },
      "indexes": {},
      "foreignKeys": {},
      "compositePrimaryKeys": {},
      "uniqueConstraints": {
        "permission_id_unique": {
          "name": "permission_id_unique",
          "nullsNotDistinct": false,
          "columns": [
            "id"
          ]
        }
      }
    },
    "permission_role": {
      "name": "permission_role",
      "schema": "",
      "columns": {
        "role_id": {
          "name": "role_id",
          "type": "uuid",
          "primaryKey": false,
          "notNull": true
        },
        "permission_id": {
          "name": "permission_id",
          "type": "uuid",
          "primaryKey": false,
          "notNull": true
        }
      },
      "indexes": {},
      "foreignKeys": {
        "permission_role_role_id_role_id_fk": {
          "name": "permission_role_role_id_role_id_fk",
          "tableFrom": "permission_role",
          "tableTo": "role",
          "columnsFrom": [
            "role_id"
          ],
          "columnsTo": [
            "id"
          ],
          "onDelete": "no action",
          "onUpdate": "no action"
        },
        "permission_role_permission_id_permission_id_fk": {
          "name": "permission_role_permission_id_permission_id_fk",
          "tableFrom": "permission_role",
          "tableTo": "permission",
          "columnsFrom": [
            "permission_id"
          ],
          "columnsTo": [
            "id"
          ],
          "onDelete": "no action",
          "onUpdate": "no action"
        }
      },
      "compositePrimaryKeys": {
        "permission_role_role_id_permission_id_pk": {
          "name": "permission_role_role_id_permission_id_pk",
          "columns": [
            "role_id",
            "permission_id"
          ]
        }
      },
      "uniqueConstraints": {}
    },
    "purchase_anime_episode": {
      "name": "purchase_anime_episode",
      "schema": "",
      "columns": {
        "id": {
          "name": "id",
          "type": "uuid",
          "primaryKey": true,
          "notNull": true,
          "default": "gen_random_uuid()"
        },
        "user_id": {
          "name": "user_id",
          "type": "uuid",
          "primaryKey": false,
          "notNull": true
        },
        "episode_id": {
          "name": "episode_id",
          "type": "uuid",
          "primaryKey": false,
          "notNull": true
        },
        "created_at": {
          "name": "created_at",
          "type": "timestamp",
          "primaryKey": false,
          "notNull": false,
          "default": "now()"
        }
      },
      "indexes": {
        "user_purchase_anime_ep_idx": {
          "name": "user_purchase_anime_ep_idx",
          "columns": [
            "user_id"
          ],
          "isUnique": false
        },
        "anime_ep_purchased_idx": {
          "name": "anime_ep_purchased_idx",
          "columns": [
            "episode_id"
          ],
          "isUnique": false
        }
      },
      "foreignKeys": {
        "purchase_anime_episode_user_id_user_id_fk": {
          "name": "purchase_anime_episode_user_id_user_id_fk",
          "tableFrom": "purchase_anime_episode",
          "tableTo": "user",
          "columnsFrom": [
            "user_id"
          ],
          "columnsTo": [
            "id"
          ],
          "onDelete": "cascade",
          "onUpdate": "no action"
        },
        "purchase_anime_episode_episode_id_anime_episode_id_fk": {
          "name": "purchase_anime_episode_episode_id_anime_episode_id_fk",
          "tableFrom": "purchase_anime_episode",
          "tableTo": "anime_episode",
          "columnsFrom": [
            "episode_id"
          ],
          "columnsTo": [
            "id"
          ],
          "onDelete": "cascade",
          "onUpdate": "no action"
        }
      },
      "compositePrimaryKeys": {},
      "uniqueConstraints": {
        "purchase_anime_episode_id_unique": {
          "name": "purchase_anime_episode_id_unique",
          "nullsNotDistinct": false,
          "columns": [
            "id"
          ]
        }
      }
    },
    "purchase_lightnovel_chapter": {
      "name": "purchase_lightnovel_chapter",
      "schema": "",
      "columns": {
        "id": {
          "name": "id",
          "type": "uuid",
          "primaryKey": true,
          "notNull": true,
          "default": "gen_random_uuid()"
        },
        "user_id": {
          "name": "user_id",
          "type": "uuid",
          "primaryKey": false,
          "notNull": true
        },
        "chapter_id": {
          "name": "chapter_id",
          "type": "uuid",
          "primaryKey": false,
          "notNull": true
        },
        "created_at": {
          "name": "created_at",
          "type": "timestamp",
          "primaryKey": false,
          "notNull": false,
          "default": "now()"
        }
      },
      "indexes": {
        "user_purchase_lightnovel_chapter_idx": {
          "name": "user_purchase_lightnovel_chapter_idx",
          "columns": [
            "user_id"
          ],
          "isUnique": false
        },
        "lightnovel_chapter_purchased_idx": {
          "name": "lightnovel_chapter_purchased_idx",
          "columns": [
            "chapter_id"
          ],
          "isUnique": false
        }
      },
      "foreignKeys": {
        "purchase_lightnovel_chapter_user_id_user_id_fk": {
          "name": "purchase_lightnovel_chapter_user_id_user_id_fk",
          "tableFrom": "purchase_lightnovel_chapter",
          "tableTo": "user",
          "columnsFrom": [
            "user_id"
          ],
          "columnsTo": [
            "id"
          ],
          "onDelete": "cascade",
          "onUpdate": "no action"
        },
        "purchase_lightnovel_chapter_chapter_id_lightnovel_chapter_id_fk": {
          "name": "purchase_lightnovel_chapter_chapter_id_lightnovel_chapter_id_fk",
          "tableFrom": "purchase_lightnovel_chapter",
          "tableTo": "lightnovel_chapter",
          "columnsFrom": [
            "chapter_id"
          ],
          "columnsTo": [
            "id"
          ],
          "onDelete": "cascade",
          "onUpdate": "no action"
        }
      },
      "compositePrimaryKeys": {},
      "uniqueConstraints": {
        "purchase_lightnovel_chapter_id_unique": {
          "name": "purchase_lightnovel_chapter_id_unique",
          "nullsNotDistinct": false,
          "columns": [
            "id"
          ]
        }
      }
    },
    "purchase_manga_chapter": {
      "name": "purchase_manga_chapter",
      "schema": "",
      "columns": {
        "id": {
          "name": "id",
          "type": "uuid",
          "primaryKey": true,
          "notNull": true,
          "default": "gen_random_uuid()"
        },
        "user_id": {
          "name": "user_id",
          "type": "uuid",
          "primaryKey": false,
          "notNull": true
        },
        "chapter_id": {
          "name": "chapter_id",
          "type": "uuid",
          "primaryKey": false,
          "notNull": true
        },
        "created_at": {
          "name": "created_at",
          "type": "timestamp",
          "primaryKey": false,
          "notNull": false,
          "default": "now()"
        }
      },
      "indexes": {
        "user_purchase_manga_chapter_idx": {
          "name": "user_purchase_manga_chapter_idx",
          "columns": [
            "user_id"
          ],
          "isUnique": false
        },
        "manga_chapter_purchased_idx": {
          "name": "manga_chapter_purchased_idx",
          "columns": [
            "chapter_id"
          ],
          "isUnique": false
        }
      },
      "foreignKeys": {
        "purchase_manga_chapter_user_id_user_id_fk": {
          "name": "purchase_manga_chapter_user_id_user_id_fk",
          "tableFrom": "purchase_manga_chapter",
          "tableTo": "user",
          "columnsFrom": [
            "user_id"
          ],
          "columnsTo": [
            "id"
          ],
          "onDelete": "cascade",
          "onUpdate": "no action"
        },
        "purchase_manga_chapter_chapter_id_manga_chapter_id_fk": {
          "name": "purchase_manga_chapter_chapter_id_manga_chapter_id_fk",
          "tableFrom": "purchase_manga_chapter",
          "tableTo": "manga_chapter",
          "columnsFrom": [
            "chapter_id"
          ],
          "columnsTo": [
            "id"
          ],
          "onDelete": "cascade",
          "onUpdate": "no action"
        }
      },
      "compositePrimaryKeys": {},
      "uniqueConstraints": {
        "purchase_manga_chapter_id_unique": {
          "name": "purchase_manga_chapter_id_unique",
          "nullsNotDistinct": false,
          "columns": [
            "id"
          ]
        }
      }
    },
    "rating": {
      "name": "rating",
      "schema": "",
      "columns": {
        "id": {
          "name": "id",
          "type": "uuid",
          "primaryKey": true,
          "notNull": true,
          "default": "gen_random_uuid()"
        },
        "score": {
          "name": "score",
          "type": "integer",
          "primaryKey": false,
          "notNull": true,
          "default": 0
        },
        "user_id": {
          "name": "user_id",
          "type": "uuid",
          "primaryKey": false,
          "notNull": true
        },
        "lightnovel_id": {
          "name": "lightnovel_id",
          "type": "uuid",
          "primaryKey": false,
          "notNull": false
        },
        "anime_id": {
          "name": "anime_id",
          "type": "uuid",
          "primaryKey": false,
          "notNull": false
        },
        "manga_id": {
          "name": "manga_id",
          "type": "uuid",
          "primaryKey": false,
          "notNull": false
        }
      },
      "indexes": {},
      "foreignKeys": {
        "rating_user_id_user_id_fk": {
          "name": "rating_user_id_user_id_fk",
          "tableFrom": "rating",
          "tableTo": "user",
          "columnsFrom": [
            "user_id"
          ],
          "columnsTo": [
            "id"
          ],
          "onDelete": "cascade",
          "onUpdate": "no action"
        }
      },
      "compositePrimaryKeys": {},
      "uniqueConstraints": {
        "rating_id_unique": {
          "name": "rating_id_unique",
          "nullsNotDistinct": false,
          "columns": [
            "id"
          ]
        }
      }
    },
    "reset_password_token": {
      "name": "reset_password_token",
      "schema": "",
      "columns": {
        "id": {
          "name": "id",
          "type": "uuid",
          "primaryKey": true,
          "notNull": true,
          "default": "gen_random_uuid()"
        },
        "email": {
          "name": "email",
          "type": "text",
          "primaryKey": false,
          "notNull": true
        },
        "token": {
          "name": "token",
          "type": "text",
          "primaryKey": false,
          "notNull": true
        },
        "expires": {
          "name": "expires",
          "type": "timestamp",
          "primaryKey": false,
          "notNull": true
        }
      },
      "indexes": {},
      "foreignKeys": {},
      "compositePrimaryKeys": {},
      "uniqueConstraints": {
        "reset_password_token_id_unique": {
          "name": "reset_password_token_id_unique",
          "nullsNotDistinct": false,
          "columns": [
            "id"
          ]
        },
        "reset_password_token_email_unique": {
          "name": "reset_password_token_email_unique",
          "nullsNotDistinct": false,
          "columns": [
            "email"
          ]
        },
        "reset_password_token_token_unique": {
          "name": "reset_password_token_token_unique",
          "nullsNotDistinct": false,
          "columns": [
            "token"
          ]
        }
      }
    },
    "role": {
      "name": "role",
      "schema": "",
      "columns": {
        "id": {
          "name": "id",
          "type": "uuid",
          "primaryKey": true,
          "notNull": true,
          "default": "gen_random_uuid()"
        },
        "name": {
          "name": "name",
          "type": "text",
          "primaryKey": false,
          "notNull": true
        }
      },
      "indexes": {},
      "foreignKeys": {},
      "compositePrimaryKeys": {},
      "uniqueConstraints": {
        "role_id_unique": {
          "name": "role_id_unique",
          "nullsNotDistinct": false,
          "columns": [
            "id"
          ]
        }
      }
    },
    "transaction_fee_anime": {
      "name": "transaction_fee_anime",
      "schema": "",
      "columns": {
        "id": {
          "name": "id",
          "type": "uuid",
          "primaryKey": true,
          "notNull": true,
          "default": "gen_random_uuid()"
        },
        "transaction": {
          "name": "transaction",
          "type": "uuid",
          "primaryKey": false,
          "notNull": true
        },
        "amount": {
          "name": "amount",
          "type": "integer",
          "primaryKey": false,
          "notNull": true
        }
      },
      "indexes": {
        "transaction_fee_anime_idx": {
          "name": "transaction_fee_anime_idx",
          "columns": [
            "transaction"
          ],
          "isUnique": false
        }
      },
      "foreignKeys": {
        "transaction_fee_anime_transaction_purchase_anime_episode_id_fk": {
          "name": "transaction_fee_anime_transaction_purchase_anime_episode_id_fk",
          "tableFrom": "transaction_fee_anime",
          "tableTo": "purchase_anime_episode",
          "columnsFrom": [
            "transaction"
          ],
          "columnsTo": [
            "id"
          ],
          "onDelete": "cascade",
          "onUpdate": "no action"
        }
      },
      "compositePrimaryKeys": {},
      "uniqueConstraints": {
        "transaction_fee_anime_id_unique": {
          "name": "transaction_fee_anime_id_unique",
          "nullsNotDistinct": false,
          "columns": [
            "id"
          ]
        }
      }
    },
    "transaction_fee_lightnovel": {
      "name": "transaction_fee_lightnovel",
      "schema": "",
      "columns": {
        "id": {
          "name": "id",
          "type": "uuid",
          "primaryKey": true,
          "notNull": true,
          "default": "gen_random_uuid()"
        },
        "transaction": {
          "name": "transaction",
          "type": "uuid",
          "primaryKey": false,
          "notNull": true
        },
        "amount": {
          "name": "amount",
          "type": "integer",
          "primaryKey": false,
          "notNull": true
        }
      },
      "indexes": {
        "transaction_fee_lightnovel_idx": {
          "name": "transaction_fee_lightnovel_idx",
          "columns": [
            "transaction"
          ],
          "isUnique": false
        }
      },
      "foreignKeys": {
        "transaction_fee_lightnovel_transaction_purchase_lightnovel_chapter_id_fk": {
          "name": "transaction_fee_lightnovel_transaction_purchase_lightnovel_chapter_id_fk",
          "tableFrom": "transaction_fee_lightnovel",
          "tableTo": "purchase_lightnovel_chapter",
          "columnsFrom": [
            "transaction"
          ],
          "columnsTo": [
            "id"
          ],
          "onDelete": "cascade",
          "onUpdate": "no action"
        }
      },
      "compositePrimaryKeys": {},
      "uniqueConstraints": {
        "transaction_fee_lightnovel_id_unique": {
          "name": "transaction_fee_lightnovel_id_unique",
          "nullsNotDistinct": false,
          "columns": [
            "id"
          ]
        }
      }
    },
    "transaction_fee_manga": {
      "name": "transaction_fee_manga",
      "schema": "",
      "columns": {
        "id": {
          "name": "id",
          "type": "uuid",
          "primaryKey": true,
          "notNull": true,
          "default": "gen_random_uuid()"
        },
        "transaction": {
          "name": "transaction",
          "type": "uuid",
          "primaryKey": false,
          "notNull": true
        },
        "amount": {
          "name": "amount",
          "type": "integer",
          "primaryKey": false,
          "notNull": true
        }
      },
      "indexes": {
        "transaction_fee_manga_idx": {
          "name": "transaction_fee_manga_idx",
          "columns": [
            "transaction"
          ],
          "isUnique": false
        }
      },
      "foreignKeys": {
        "transaction_fee_manga_transaction_purchase_manga_chapter_id_fk": {
          "name": "transaction_fee_manga_transaction_purchase_manga_chapter_id_fk",
          "tableFrom": "transaction_fee_manga",
          "tableTo": "purchase_manga_chapter",
          "columnsFrom": [
            "transaction"
          ],
          "columnsTo": [
            "id"
          ],
          "onDelete": "cascade",
          "onUpdate": "no action"
        }
      },
      "compositePrimaryKeys": {},
      "uniqueConstraints": {
        "transaction_fee_manga_id_unique": {
          "name": "transaction_fee_manga_id_unique",
          "nullsNotDistinct": false,
          "columns": [
            "id"
          ]
        }
      }
    },
    "translation_group": {
      "name": "translation_group",
      "schema": "",
      "columns": {
        "id": {
          "name": "id",
          "type": "uuid",
          "primaryKey": true,
          "notNull": true,
          "default": "gen_random_uuid()"
        },
        "description": {
          "name": "description",
          "type": "jsonb",
          "primaryKey": false,
          "notNull": false
        },
        "name": {
          "name": "name",
          "type": "text",
          "primaryKey": false,
          "notNull": true
        },
        "image": {
          "name": "image",
          "type": "jsonb",
          "primaryKey": false,
          "notNull": false,
          "default": "'{\"key\":\"\",\"url\":\"\"}'::jsonb"
        },
        "user_id": {
          "name": "user_id",
          "type": "uuid",
          "primaryKey": false,
          "notNull": false
        }
      },
      "indexes": {
        "translation_group_name_idx": {
          "name": "translation_group_name_idx",
          "columns": [
            "name"
          ],
          "isUnique": false
        }
      },
      "foreignKeys": {
        "translation_group_user_id_user_id_fk": {
          "name": "translation_group_user_id_user_id_fk",
          "tableFrom": "translation_group",
          "tableTo": "user",
          "columnsFrom": [
            "user_id"
          ],
          "columnsTo": [
            "id"
          ],
          "onDelete": "cascade",
          "onUpdate": "no action"
        }
      },
      "compositePrimaryKeys": {},
      "uniqueConstraints": {
        "translation_group_id_unique": {
          "name": "translation_group_id_unique",
          "nullsNotDistinct": false,
          "columns": [
            "id"
          ]
        }
      }
    },
    "translation_group_members": {
      "name": "translation_group_members",
      "schema": "",
      "columns": {
        "user_id": {
          "name": "user_id",
          "type": "uuid",
          "primaryKey": false,
          "notNull": true
        },
        "group_id": {
          "name": "group_id",
          "type": "uuid",
          "primaryKey": false,
          "notNull": true
        }
      },
      "indexes": {},
      "foreignKeys": {
        "translation_group_members_user_id_user_id_fk": {
          "name": "translation_group_members_user_id_user_id_fk",
          "tableFrom": "translation_group_members",
          "tableTo": "user",
          "columnsFrom": [
            "user_id"
          ],
          "columnsTo": [
            "id"
          ],
          "onDelete": "no action",
          "onUpdate": "no action"
        },
        "translation_group_members_group_id_translation_group_id_fk": {
          "name": "translation_group_members_group_id_translation_group_id_fk",
          "tableFrom": "translation_group_members",
          "tableTo": "translation_group",
          "columnsFrom": [
            "group_id"
          ],
          "columnsTo": [
            "id"
          ],
          "onDelete": "no action",
          "onUpdate": "no action"
        }
      },
      "compositePrimaryKeys": {
        "translation_group_members_user_id_group_id_pk": {
          "name": "translation_group_members_user_id_group_id_pk",
          "columns": [
            "user_id",
            "group_id"
          ]
        }
      },
      "uniqueConstraints": {}
    },
    "user_roles": {
      "name": "user_roles",
      "schema": "",
      "columns": {
        "user_id": {
          "name": "user_id",
          "type": "uuid",
          "primaryKey": false,
          "notNull": true
        },
        "role_id": {
          "name": "role_id",
          "type": "uuid",
          "primaryKey": false,
          "notNull": true
        }
      },
      "indexes": {},
      "foreignKeys": {
        "user_roles_user_id_user_id_fk": {
          "name": "user_roles_user_id_user_id_fk",
          "tableFrom": "user_roles",
          "tableTo": "user",
          "columnsFrom": [
            "user_id"
          ],
          "columnsTo": [
            "id"
          ],
          "onDelete": "no action",
          "onUpdate": "no action"
        },
        "user_roles_role_id_role_id_fk": {
          "name": "user_roles_role_id_role_id_fk",
          "tableFrom": "user_roles",
          "tableTo": "role",
          "columnsFrom": [
            "role_id"
          ],
          "columnsTo": [
            "id"
          ],
          "onDelete": "no action",
          "onUpdate": "no action"
        }
      },
      "compositePrimaryKeys": {
        "user_roles_user_id_role_id_pk": {
          "name": "user_roles_user_id_role_id_pk",
          "columns": [
            "user_id",
            "role_id"
          ]
        }
      },
      "uniqueConstraints": {}
    },
    "user": {
      "name": "user",
      "schema": "",
      "columns": {
        "id": {
          "name": "id",
          "type": "uuid",
          "primaryKey": true,
          "notNull": true,
          "default": "gen_random_uuid()"
        },
        "name": {
          "name": "name",
          "type": "text",
          "primaryKey": false,
          "notNull": true
        },
        "username": {
          "name": "username",
          "type": "text",
          "primaryKey": false,
          "notNull": false
        },
        "image": {
          "name": "image",
          "type": "text",
          "primaryKey": false,
          "notNull": false
        },
        "coins": {
          "name": "coins",
          "type": "integer",
          "primaryKey": false,
          "notNull": false,
          "default": 0
        },
        "image_key": {
          "name": "image_key",
          "type": "text",
          "primaryKey": false,
          "notNull": false,
          "default": "''"
        },
        "description": {
          "name": "description",
          "type": "jsonb",
          "primaryKey": false,
          "notNull": false
        },
        "email": {
          "name": "email",
          "type": "text",
          "primaryKey": false,
          "notNull": true
        },
        "phone": {
          "name": "phone",
          "type": "text",
          "primaryKey": false,
          "notNull": false
        },
        "hashed_password": {
          "name": "hashed_password",
          "type": "text",
          "primaryKey": false,
          "notNull": false
        },
        "emailVerified": {
          "name": "emailVerified",
          "type": "boolean",
          "primaryKey": false,
          "notNull": false,
          "default": false
        },
        "phoneVerified": {
          "name": "phoneVerified",
          "type": "boolean",
          "primaryKey": false,
          "notNull": false,
          "default": false
        },
        "created_at": {
          "name": "created_at",
          "type": "timestamp",
          "primaryKey": false,
          "notNull": false,
          "default": "now()"
        },
        "updated_at": {
          "name": "updated_at",
          "type": "timestamp",
          "primaryKey": false,
          "notNull": false,
          "default": "now()"
        }
      },
      "indexes": {
        "user_name_idx": {
          "name": "user_name_idx",
          "columns": [
            "name"
          ],
          "isUnique": false
        },
        "user_username_idx": {
          "name": "user_username_idx",
          "columns": [
            "username"
          ],
          "isUnique": false
        }
      },
      "foreignKeys": {},
      "compositePrimaryKeys": {},
      "uniqueConstraints": {
        "user_id_unique": {
          "name": "user_id_unique",
          "nullsNotDistinct": false,
          "columns": [
            "id"
          ]
        },
        "user_username_unique": {
          "name": "user_username_unique",
          "nullsNotDistinct": false,
          "columns": [
            "username"
          ]
        },
        "user_email_unique": {
          "name": "user_email_unique",
          "nullsNotDistinct": false,
          "columns": [
            "email"
          ]
        },
        "user_phone_unique": {
          "name": "user_phone_unique",
          "nullsNotDistinct": false,
          "columns": [
            "phone"
          ]
        }
      }
    },
    "verification_token": {
      "name": "verification_token",
      "schema": "",
      "columns": {
        "id": {
          "name": "id",
          "type": "uuid",
          "primaryKey": true,
          "notNull": true,
          "default": "gen_random_uuid()"
        },
        "email": {
          "name": "email",
          "type": "text",
          "primaryKey": false,
          "notNull": true
        },
        "token": {
          "name": "token",
          "type": "text",
          "primaryKey": false,
          "notNull": true
        },
        "expires": {
          "name": "expires",
          "type": "timestamp",
          "primaryKey": false,
          "notNull": true
        }
      },
      "indexes": {},
      "foreignKeys": {},
      "compositePrimaryKeys": {},
      "uniqueConstraints": {
        "verification_token_id_unique": {
          "name": "verification_token_id_unique",
          "nullsNotDistinct": false,
          "columns": [
            "id"
          ]
        },
        "verification_token_email_unique": {
          "name": "verification_token_email_unique",
          "nullsNotDistinct": false,
          "columns": [
            "email"
          ]
        },
        "verification_token_token_unique": {
          "name": "verification_token_token_unique",
          "nullsNotDistinct": false,
          "columns": [
            "token"
          ]
        }
      }
    }
  },
  "enums": {},
  "schemas": {},
  "_meta": {
    "columns": {},
    "schemas": {},
    "tables": {}
  }
}